adp_api_converter/__init__.py
adp_api_converter/__main__.py
adp_api_transformeer-0.0.2.dist-info/licenses/LICENSE
adp_api_transformeer-0.0.2.dist-info/METADATA
adp_api_transformeer-0.0.2.dist-info/WHEEL
adp_api_transformeer-0.0.2.dist-info/entry_points.txt
adp_api_transformeer-0.0.2.dist-info/top_level.txt
adp_api_transformeer-0.0.2.dist-info/RECORD
