Metadata-Version: 2.4
Name: adp-api-transformeer
Version: 0.0.2
Summary: This package can be used to transform your openapi specs (json or yaml) to be used in the ADP1 apim repo
Author-email: Peter De Winne <peter.dewinne@delaware.pro>, Thibo Cuveele <thibo.cuveele@delaware.pro>
Classifier: Programming Language :: Python :: 3
Classifier: Operating System :: OS Independent
Requires-Python: >=3.9
License-File: LICENSE
Requires-Dist: pyyaml
Dynamic: license-file
